{
	"class" : {
		"on:" : " 11/06/2017 11:28:40",
		"parseStream:" : " 11/06/2017 11:28:40",
		"parseString:" : " 11/06/2017 11:28:40" },
	"instance" : {
		"cleanSelector:" : " 11/06/2017 11:28:40",
		"comment" : " 11/06/2017 11:28:40",
		"definitionForType:" : " 11/06/2017 11:28:40",
		"document" : " 11/06/2017 11:28:40",
		"extractSelector:" : " 11/06/2017 11:28:40",
		"isEnter:" : " 11/06/2017 11:28:40",
		"isSeparator:" : " 11/06/2017 11:28:40",
		"metadata" : " 11/06/2017 11:28:40",
		"method" : " 11/06/2017 11:28:40",
		"methodBody" : " 11/06/2017 11:28:40",
		"methodDef" : " 11/06/2017 11:28:40",
		"methodDefList" : " 11/06/2017 11:28:40",
		"newClassDefinitionFrom:" : " 11/06/2017 11:28:40",
		"newMethodDefinitionFrom:" : " 11/06/2017 11:28:40",
		"newTraitDefinitionFrom:" : " 11/06/2017 11:28:40",
		"newTypeDefinitionFrom:" : " 11/06/2017 11:28:40",
		"removeFrom:enclosingStart:end:" : " 11/06/2017 11:28:40",
		"removeFrom:enclosingStart:end:clean:" : "dkh 11/06/2017 12:14",
		"separator" : " 11/06/2017 11:28:40",
		"start" : " 11/06/2017 11:28:40",
		"stream:" : " 11/06/2017 11:28:40",
		"try:" : " 11/06/2017 11:28:40",
		"try:onFailure:" : " 11/06/2017 11:28:40",
		"try:onSuccess:" : " 11/06/2017 11:28:40",
		"try:onSuccess:onFailure:" : " 11/06/2017 11:28:40",
		"type" : " 11/06/2017 11:28:40",
		"typeDef" : " 11/06/2017 11:28:40",
		"untilExcluding:" : " 11/06/2017 11:28:40",
		"untilIncluding:" : " 11/06/2017 11:28:40",
		"word:" : " 11/06/2017 11:28:40" } }
